utci/__init__.py
utci/_version.py
utci/py.typed
utci/utci.py
utci-1.0.0.dist-info/licenses/LICENSE
utci-1.0.0.dist-info/METADATA
utci-1.0.0.dist-info/WHEEL
utci-1.0.0.dist-info/top_level.txt
utci-1.0.0.dist-info/RECORD
