Metadata-Version: 2.4
Name: utci
Version: 1.0.0
Summary: Python implementation of Universal Thermal Climate Index (UTCI)
Author-email: Alex Zemliakov <alex@ndr.su>
Maintainer-email: Alex Zemliakov <alex@ndr.su>
License: MIT
Project-URL: Homepage, https://github.com/marvell/utci
Project-URL: Repository, https://github.com/marvell/utci
Project-URL: Documentation, https://github.com/marvell/utci#readme
Project-URL: Bug Tracker, https://github.com/marvell/utci/issues
Project-URL: Changelog, https://github.com/marvell/utci/blob/main/CHANGELOG.md
Keywords: utci,thermal-comfort,biometeorology,climate,temperature,heat-index,thermal-stress,environmental-science
Classifier: Development Status :: 5 - Production/Stable
Classifier: Intended Audience :: Science/Research
Classifier: Intended Audience :: Developers
Classifier: Topic :: Scientific/Engineering :: Atmospheric Science
Classifier: License :: OSI Approved :: MIT License
Classifier: Programming Language :: Python :: 3
Classifier: Programming Language :: Python :: 3.8
Classifier: Programming Language :: Python :: 3.9
Classifier: Programming Language :: Python :: 3.10
Classifier: Programming Language :: Python :: 3.11
Classifier: Programming Language :: Python :: 3.12
Classifier: Operating System :: OS Independent
Classifier: Typing :: Typed
Requires-Python: >=3.8
License-File: LICENSE
Requires-Dist: numpy>=1.20.0
Provides-Extra: dev
Requires-Dist: pytest>=7.0.0; extra == "dev"
Requires-Dist: pytest-cov>=4.0.0; extra == "dev"
Requires-Dist: mypy>=1.0.0; extra == "dev"
Requires-Dist: ruff>=0.1.0; extra == "dev"
Requires-Dist: black>=23.0.0; extra == "dev"
Requires-Dist: isort>=5.0.0; extra == "dev"
Requires-Dist: pre-commit>=3.0.0; extra == "dev"
Provides-Extra: docs
Requires-Dist: sphinx>=5.0.0; extra == "docs"
Requires-Dist: sphinx-rtd-theme>=1.0.0; extra == "docs"
Requires-Dist: sphinx-autodoc-typehints>=1.0.0; extra == "docs"
Provides-Extra: test
Requires-Dist: pytest>=7.0.0; extra == "test"
Requires-Dist: pytest-cov>=4.0.0; extra == "test"
Requires-Dist: tox>=4.0.0; extra == "test"
Dynamic: license-file
